[{"s": "h96-max-4k-ultra-hd-ne-vklyuchaetsya-krasnyj-ogonek", "t": "H96 Max 4K не включается: горит красный индикатор — причины и ремонт", "i": "📁", "c": null}, {"s": "h96-max-dublirovat-ekran-noutbuka", "t": "H96 Max: как дублировать экран ноутбука через HDMI и Wi-Fi", "i": "🖥️", "c": "noutbuki-i-zhelezo"}, {"s": "h96-max-h616-gorit-nadpis-boot", "t": "H96 Max H616 горит надпись Boot: полное руководство по ремонту", "i": "📁", "c": null}, {"s": "h96-max-ne-zagruzhaetsya-posle-ustanovki-arabian", "t": "H96 Max не загружается после Arabian: решение проблемы", "i": "📁", "c": null}, {"s": "h96-max-v11-ne-vklyuchaetsya", "t": "H96 Max V11 не включается: ремонт, прошивка, диагностика", "i": "📁", "c": null}, {"s": "h96max-4k-ultra-hd-ne-vklyuchaetsya", "t": "H96MAX 4K Ultra HD не включается: причины и решение", "i": "📁", "c": null}, {"s": "h96max-ne-vklyuchaetsya-gorit-krasnyj", "t": "H96 Max не включается и горит красный: решение проблемы", "i": "📁", "c": null}, {"s": "h96max-rk3528-podklyuchit-telefon", "t": "H96MAX RK3528: как подключить телефон к ТВ", "i": "📱", "c": "mobilnye-os"}, {"s": "h96max-soedinenie-s-telefonom", "t": "H96 Max соединение с телефоном: полная инструкция", "i": "📱", "c": "mobilnye-os"}]