[{"s": "do-alt-mode-redmi-nout-12", "t": "Do Alt Mode Redmi Note 12: Поддержка видео через USB-C", "i": "📁", "c": null}, {"s": "dobavit-forkplayer-v-mxstation", "t": "Как добавить ForkPlayer в MXStation: Полная инструкция", "i": "📱", "c": "prilozheniya-servisy"}, {"s": "dobavit-na-panel-v-excel-smart-view", "t": "Как добавить Smart View на панель Excel: Полная инструкция", "i": "📺", "c": "nastroika-tv"}, {"s": "dobavit-plejlist-peers-tv-2025", "t": "Как добавить плейлист Peers TV 2026: Полная инструкция", "i": "📺", "c": "nastroika-tv"}, {"s": "dobavit-prilozheniya-v-telefunken", "t": "Как добавить приложения в телевизоры Telefunken: Полная инструкция 2026", "i": "📁", "c": null}, {"s": "dobavit-ustrojstvo-na-kinopab", "t": "Как добавить устройство на Кинопаб: полная инструкция по привязке", "i": "📺", "c": "nastroika-tv"}, {"s": "dobavit-vidzhety-na-chasy-amazfit-gtr-2", "t": "Как добавить виджеты на часы Amazfit GTR 2: полная инструкция", "i": "📁", "c": null}, {"s": "dobavlenie-mail-v-gmail", "t": "Как добавить почту в Gmail: Полная инструкция по настройке", "i": "📁", "c": null}, {"s": "dobavleniya-propuska-v-iphone", "t": "Как добавить пропуск в iPhone: полная инструкция 2026", "i": "🍎", "c": "apple-ustroystva"}, {"s": "dobryninskij-vhod-v-prilozhenie-net", "t": "Добрынинский вход в приложение нет: Как исправить проблему на Android TV", "i": "🤖", "c": "smartfony-android"}, {"s": "doffler-32ghs67-ustanovka-storonnih-prilozhenij", "t": "Установка сторонних приложений на Doffler 32GHS67: Полное руководство", "i": "📁", "c": null}, {"s": "doffler-televizor-ustanovit-kinopoisk", "t": "Как установить Кинопоиск на телевизор Doffler: полная инструкция", "i": "📺", "c": "nastroika-tv"}, {"s": "dolgo-idut-sms-na-feniks", "t": "Долго идут СМС на Феникс: причины, решение и настройка скорости", "i": "📁", "c": null}, {"s": "dolgo-vklyuchaetsya-televizor-kivi", "t": "Долго включается телевизор Kivi: причины и способы устранения", "i": "📺", "c": "nastroika-tv"}, {"s": "dolgoe-proverka-i-vosstanovlenie-fleshki", "t": "Долгая проверка и восстановление флешки: причины и решения", "i": "📁", "c": null}, {"s": "dollar-v-chehle-dlya-telefona-zachem-nuzhen", "t": "Доллар в чехле для телефона: Зачем нужен и как работает?", "i": "📁", "c": null}, {"s": "dom-kinoteatr-lg-bh", "t": "Дом кинотеатр LG BH: Полное руководство по настройке и обзору", "i": "📁", "c": null}, {"s": "dom-ru-otklyuchit-podpisku", "t": "Как отключить подписку Дом.ру: пошаговая инструкция 2026", "i": "📁", "c": null}, {"s": "dom-ru-smenit-tarif-na-bolee-deshevyj-kak", "t": "Как сменить тариф Дом.ru на более дешевый: пошаговая инструкция", "i": "📁", "c": null}, {"s": "dom-ru-zavisla-pristavka-ne-reagiruet-na-pult", "t": "Приставка Дом.ru зависла: полное руководство по решению", "i": "📡", "c": "tv-pristavki"}, {"s": "doma-dva-2-televizora-lg-pereklyuchaesh-odin-televizor-zadejstvuet-vtoroj-kak", "t": "Как отвязать телевизоры LG: убираем синхронизацию управления", "i": "📺", "c": "nastroika-tv"}, {"s": "domashnie-pticy-kakuyu-vybrat-v9-provider-windows", "t": "Домашние птицы и V9 Provider Windows: Выбор, установка, ошибки", "i": "💻", "c": "noutbuki-pk"}, {"s": "domashnij-internet-yandeks", "t": "Домашний интернет Яндекс: тарифы, роутеры и подключение 2026", "i": "🌐", "c": "set-i-internet"}, {"s": "domashnij-kinoteatr-sony", "t": "Домашний кинотеатр Sony: выбор, настройка и лучшие модели 2026", "i": "🎮", "c": "audio-i-geyming"}, {"s": "domashnij-kinoteatr-vid-szadi-razemy-s-hdmi", "t": "Разъемы HDMI сзади домашнего кинотеатра: полный гид по подключению", "i": "📺", "c": "nastroika-tv"}, {"s": "domashnij-server-dns", "t": "Домашний сервер DNS: Полное руководство по настройке и безопасности", "i": "🌐", "c": "set-i-internet"}, {"s": "donat-dlya-lazymedia-deluxe", "t": "Донат для LazyMedia Deluxe: как поддержать разработчиков и получить бонусы", "i": "📁", "c": null}, {"s": "dongle-joys-d20-driver", "t": "Драйвер Dongle JoyS D20: скачивание, установка и настройка", "i": "💻", "c": "noutbuki-pk"}, {"s": "dop-prilozhenie-i-quickstep-na-androide-ne-otvechayut", "t": "Чиним ошибку: Допприложение и Quickstep не отвечают на Android", "i": "📺", "c": "nastroika-tv"}, {"s": "dopolnitelnye-otverstiya-v-noutbuke-dlya-ohlazhdeniya", "t": "Дополнительные отверстия для охлаждения ноутбука: мифы и реальность", "i": "📺", "c": "nastroika-tv"}, {"s": "dopolnitelnyj-ekran-dlya-noutbuka", "t": "Дополнительный экран для ноутбука: выбор, подключение и настройка", "i": "🤖", "c": "smartfony-android"}, {"s": "dorama-tv-prilozhenie-dlya-tv-pristavki", "t": "Приложение Дорама ТВ для Android TV: установка, настройка и обзор", "i": "📺", "c": "nastroika-tv"}, {"s": "doroma-tv-prilodenie-na-androjd", "t": "Dorama TV на Android: Полное руководство по установке и настройке", "i": "📺", "c": "nastroika-tv"}, {"s": "dos-ili-win-10", "t": "MS-DOS против Windows 10: Сравнение, выбор и мифы", "i": "📁", "c": null}, {"s": "dostup-k-tehnozon-installer", "t": "Доступ к технозоне Инсталлер: полная инструкция по входу", "i": "🔒", "c": "bezopasnost-akkaunty"}, {"s": "dostup-zapreschen-oshibka-1-v-android", "t": "Доступ запрещен ошибка 1 на Android: полные способы решения", "i": "📡", "c": "tv-pristavki"}, {"s": "dot-drop-ekran", "t": "Дот дроп экран: Как исправить разрывы и мерцание на мониторе", "i": "🤖", "c": "smartfony-android"}, {"s": "download-games-lizbiyan", "t": "Безопасная загрузка игр для Android: руководство по поиску и установке", "i": "📁", "c": null}, {"s": "dows-7-simulator-online", "t": "Windows 7 Simulator Online: Запуск легендарной ОС в браузере", "i": "📁", "c": null}, {"s": "dozhdites-zagruzki-pered-otkrytiem-prilozheniya-redmi", "t": "Ошибка Redmi: Дождитесь загрузки перед открытием приложения", "i": "📁", "c": null}]