[{"s": "x96-instrukciya-kak-nastroit-pult-k-televizoru-bez-pulta", "t": "X96 Инструкция: Настройка пульта к ТВ без пульта (2026)", "i": "📺", "c": "nastroika-tv"}, {"s": "x96-max-kak-vklyuchit-bez-pulta", "t": "Как включить X96 Max без пульта: 5 рабочих методов управления", "i": "📁", "c": null}, {"s": "x96-max-plus-iptv-dlya-prosmotra-osnovnyh-rossijskih-kanalov", "t": "X96 Max Plus IPTV: настройка для просмотра российских каналов", "i": "📺", "c": "nastroika-tv"}, {"s": "x96-mini-obnovit", "t": "Как обновить X96 Mini: прошивка, инструкции и частые проблемы", "i": "📁", "c": null}, {"s": "x96-mini-zagruzit-aptvi-list", "t": "Как загрузить APTV в X96 Mini: Полная инструкция по установке IPTV плеера", "i": "📺", "c": "nastroika-tv"}, {"s": "x96max-plus-4pda-kak-zapustit-bez-pulta", "t": "X96 Max Plus: как включить и настроить без пульта (полная инструкция)", "i": "📁", "c": null}, {"s": "x96q-net-kd-play", "t": "X96Q нет KD Play: Решение проблемы с отсутствием приложения", "i": "📱", "c": "prilozheniya-servisy"}, {"s": "x96q-vklyuchaetsya-bez-pulta", "t": "Как включить X96Q без пульта: 5 рабочих способов", "i": "📁", "c": null}]